{
	"animations": [
		{
			"offsets": [
				40,
				30
			],
			"loop": false,
			"fps": 24,
			"anim": "idle",
			"indices": [],
			"name": "darnell idle0"
		},
		{
			"offsets": [
				85,
				9
			],
			"loop": false,
			"fps": 24,
			"anim": "singLEFT",
			"indices": [],
			"name": "darnell left0"
		},
		{
			"offsets": [
				45,
				98
			],
			"loop": false,
			"fps": 24,
			"anim": "singUP",
			"indices": [],
			"name": "darnell up0"
		},
		{
			"offsets": [
				46,
				34
			],
			"loop": false,
			"fps": 24,
			"anim": "singRIGHT",
			"indices": [],
			"name": "darnell right0"
		},
		{
			"offsets": [
				50,
				-30
			],
			"loop": false,
			"fps": 24,
			"anim": "singDOWN",
			"indices": [],
			"name": "darnell down0"
		}
	],
	"no_antialiasing": false,
	"image": "characters/darnell",
	"position": [
		0,
		340
	],
	"healthicon": "darnell",
	"flip_x": false,
	"healthbar_colors": [
		114,
		94,
		176
	],
	"camera_position": [
		140,
		-100
	],
	"sing_duration": 4,
	"scale": 1
}