{
	"animations": [
		{
			"loop": false,
			"offsets": [
				-5,
				0
			],
			"anim": "idle",
			"fps": 24,
			"name": "BF idle dance",
			"indices": []
		},
		{
			"loop": false,
			"offsets": [
				34,
				-7
			],
			"anim": "singLEFT",
			"fps": 24,
			"name": "BF NOTE LEFT0",
			"indices": []
		},
		{
			"loop": false,
			"offsets": [
				3,
				-38
			],
			"anim": "singDOWN",
			"fps": 24,
			"name": "BF NOTE DOWN0",
			"indices": []
		},
		{
			"loop": false,
			"offsets": [
				-16,
				57
			],
			"anim": "singUP",
			"fps": 24,
			"name": "BF NOTE UP0",
			"indices": []
		},
		{
			"loop": false,
			"offsets": [
				-23,
				-7
			],
			"anim": "singRIGHT",
			"fps": 24,
			"name": "BF NOTE RIGHT0",
			"indices": []
		},
		{
			"loop": false,
			"offsets": [
				37,
				19
			],
			"anim": "singLEFTmiss",
			"fps": 24,
			"name": "BF NOTE LEFT MISS",
			"indices": []
		},
		{
			"loop": false,
			"offsets": [
				15,
				-9
			],
			"anim": "singDOWNmiss",
			"fps": 24,
			"name": "BF NOTE DOWN MISS",
			"indices": []
		},
		{
			"loop": false,
			"offsets": [
				-20,
				41
			],
			"anim": "singUPmiss",
			"fps": 24,
			"name": "BF NOTE UP MISS",
			"indices": []
		},
		{
			"loop": false,
			"offsets": [
				-22,
				-4
			],
			"anim": "singRIGHTmiss",
			"fps": 24,
			"name": "BF NOTE RIGHT MISS",
			"indices": []
		},
		{
			"loop": false,
			"offsets": [
				-3,
				5
			],
			"anim": "hey",
			"fps": 24,
			"name": "BF HEY",
			"indices": []
		},
		{
			"offsets": [
				11,
				-8
			],
			"loop": false,
			"fps": 24,
			"anim": "singLEFT-alt",
			"indices": [],
			"name": "altL"
		},
		{
			"offsets": [
				-31,
				-7
			],
			"loop": false,
			"fps": 24,
			"anim": "singRIGHT-alt",
			"indices": [],
			"name": "altR"
		},
		{
			"offsets": [
				-21,
				38
			],
			"loop": false,
			"fps": 24,
			"anim": "singUP-alt",
			"indices": [],
			"name": "altU"
		},
		{
			"offsets": [
				-19,
				-49
			],
			"loop": false,
			"fps": 24,
			"anim": "singDOWN-alt",
			"indices": [],
			"name": "altD"
		},
		{
			"offsets": [
				-8,
				0
			],
			"indices": [],
			"fps": 24,
			"anim": "no",
			"loop": false,
			"name": "7"
		},
		{
			"offsets": [
				30,
				-9
			],
			"indices": [],
			"fps": 24,
			"anim": "singLEFTmiss-alt",
			"loop": false,
			"name": "missl"
		},
		{
			"offsets": [
				-40,
				-6
			],
			"indices": [],
			"fps": 24,
			"anim": "singRIGHTmiss-alt",
			"loop": false,
			"name": "missr"
		},
		{
			"offsets": [
				-15,
				-45
			],
			"indices": [],
			"fps": 24,
			"anim": "singDOWNmiss-alt",
			"loop": false,
			"name": "missd"
		},
		{
			"offsets": [
				-51,
				43
			],
			"indices": [],
			"fps": 24,
			"anim": "singUPmiss-alt",
			"loop": false,
			"name": "missu"
		}
	],
	"no_antialiasing": false,
	"image": "characters/sportsbf",
	"position": [
		20,
		360
	],
	"healthicon": "bf",
	"flip_x": true,
	"healthbar_colors": [
		49,
		176,
		209
	],
	"camera_position": [
		0,
		10
	],
	"sing_duration": 4,
	"scale": 1
}